coin_counter/__init__.py
coin_counter/__main__.py
coin_counter/coin_counter_cli.py
coin_counter/coin_counter_gui.py
coin_counter-2.0.2.dist-info/licenses/LICENSE
coin_counter-2.0.2.dist-info/METADATA
coin_counter-2.0.2.dist-info/WHEEL
coin_counter-2.0.2.dist-info/entry_points.txt
coin_counter-2.0.2.dist-info/top_level.txt
coin_counter-2.0.2.dist-info/RECORD
