Metadata-Version: 2.4
Name: coin-counter
Version: 2.0.2
Summary: A computer vision-based coin detection and counting system with CLI and GUI interfaces
Author-email: Ibteeker Mahir Ishum <mhrisham@gmail.com>
License: MIT
Project-URL: Homepage, https://github.com/mhr-isham/Coin-Counter
Project-URL: Documentation, https://github.com/mhr-isham/Coin-Counter#readme
Project-URL: Repository, https://github.com/mhr-isham/Coin-Counter
Project-URL: Bug Tracker, https://github.com/mhr-isham/Coin-Counter/issues
Keywords: coin,counter,computer-vision,opencv,detection,image-processing
Classifier: Development Status :: 4 - Beta
Classifier: Intended Audience :: End Users/Desktop
Classifier: Intended Audience :: Developers
Classifier: Topic :: Scientific/Engineering :: Image Recognition
Classifier: Topic :: Multimedia :: Graphics :: Capture
Classifier: License :: OSI Approved :: MIT License
Classifier: Programming Language :: Python :: 3
Classifier: Programming Language :: Python :: 3.7
Classifier: Programming Language :: Python :: 3.8
Classifier: Programming Language :: Python :: 3.9
Classifier: Programming Language :: Python :: 3.10
Classifier: Programming Language :: Python :: 3.11
Classifier: Programming Language :: Python :: 3.12
Classifier: Operating System :: OS Independent
Requires-Python: >=3.7
License-File: LICENSE
Requires-Dist: opencv-python>=4.5.0
Requires-Dist: numpy>=1.19.0
Requires-Dist: matplotlib>=3.3.0
Requires-Dist: pillow>=8.0.0
Provides-Extra: dev
Requires-Dist: pytest>=7.0.0; extra == "dev"
Requires-Dist: black>=22.0.0; extra == "dev"
Requires-Dist: flake8>=4.0.0; extra == "dev"
Dynamic: license-file
